{
  "timestamp": "2026-04-19T02:38:14.844Z",
  "mode": "strict",
  "mempalaceStatus": "healthy",
  "port": 3929,
  "pid": 28956,
  "healthCheck": {
    "host": "127.0.0.1",
    "port": 3929,
    "reachable": true,
    "detail": null,
    "isMempalaceProcess": true,
    "isCurrentProjectPalace": true,
    "processName": "python.exe",
    "processCommandLine": "\"C:\\Users\\ronal\\AppData\\Local\\Programs\\Python\\Python311\\python.exe\"  \"C:\\Users\\ronal\\AppData\\Local\\Programs\\Python\\Python311\\Scripts\\mempalace.exe\" serve .mempalace --port 3929"
  },
  "errors": [],
  "ok": true
}
